nlcodec/__init__.py
nlcodec/__main__.py
nlcodec/bitextdb.py
nlcodec/bpe.py
nlcodec/codec.py
nlcodec/dstruct.py
nlcodec/learn.py
nlcodec/qestim.py
nlcodec/spark.py
nlcodec/term_freq.py
nlcodec/utils.py
nlcodec/db/__init__.py
nlcodec/db/batch.py
nlcodec/db/core.py
nlcodec/eval/__init__.py
nlcodec/eval/bpe_len.py
nlcodec/eval/oov_count.py
nlcodec/eval/pr_measure.py
nlcodec/eval/termfreq.py
nlcodec/para/__init__.py
nlcodec/para/mapred.py
nlcodec-0.5.dist-info/LICENSE
nlcodec-0.5.dist-info/METADATA
nlcodec-0.5.dist-info/WHEEL
nlcodec-0.5.dist-info/entry_points.txt
nlcodec-0.5.dist-info/top_level.txt
nlcodec-0.5.dist-info/RECORD
