Metadata-Version: 2.1
Name: nlcodec
Version: 0.5
Summary: nlcodec is a collection of encoding schemes for natural language sequences.  nlcodec.db is a efficient storage and retrieval layer for integer sequences of varying lengths.
Home-page: https://github.com/thammegowda/bpepp
Author: Thamme Gowda
Author-email: tgowdan@gmail.com
License: Apache Software License 2.0
Download-URL: https://github.com/thammegowda/bpepp
Platform: any
Classifier: Development Status :: 5 - Production/Stable
Classifier: Intended Audience :: Developers
Classifier: Topic :: Utilities
Classifier: Topic :: Text Processing
Classifier: Topic :: Text Processing :: General
Classifier: Topic :: Text Processing :: Filters
Classifier: Topic :: Text Processing :: Linguistic
Classifier: License :: OSI Approved :: Apache Software License
Classifier: Programming Language :: Python :: 3
Requires-Python: >=3.7
Requires-Dist: tqdm
Requires-Dist: numpy
